haziris/__init__.py
haziris/version.py
haziris-0.1.dist-info/LICENSE
haziris-0.1.dist-info/METADATA
haziris-0.1.dist-info/WHEEL
haziris-0.1.dist-info/top_level.txt
haziris-0.1.dist-info/RECORD
