Metadata-Version: 2.1
Name: haziris
Version: 0.1
Summary: HTML and JS Visualization templates
Home-page: http://github.com/npashap/haziris
Author: Naushad Pasha Puliyambalath
Author-email: pasha@vizjs.org
License: MIT
Platform: UNKNOWN
